scrapy_wayback_middleware/__init__.py
scrapy_wayback_middleware/middleware.py
scrapy_wayback_middleware-0.3.3.dist-info/LICENSE
scrapy_wayback_middleware-0.3.3.dist-info/WHEEL
scrapy_wayback_middleware-0.3.3.dist-info/METADATA
scrapy_wayback_middleware-0.3.3.dist-info/RECORD
