Metadata-Version: 2.1
Name: scrapy-wayback-middleware
Version: 0.3.3
Summary: Scrapy middleware for submitting URLs to the Internet Archive Wayback Machine
Home-page: https://github.com/pjsier/scrapy-wayback-middleware
License: MIT
Author: pjsier
Author-email: pjsier@gmail.com
Requires-Python: >=3.6.1,<4.0
Classifier: License :: OSI Approved :: MIT License
Classifier: Programming Language :: Python :: 3
Classifier: Programming Language :: Python :: 3.10
Classifier: Programming Language :: Python :: 3.7
Classifier: Programming Language :: Python :: 3.8
Classifier: Programming Language :: Python :: 3.9
Requires-Dist: attrs (>=17.4.0)
Requires-Dist: scrapy (>=2.0,<3.0)
Project-URL: Repository, https://github.com/pjsier/scrapy-wayback-middleware
